easySum/__init__.py
easySum/corpus.py
easySum/summarizer.py
easySum-0.2.5.dist-info/LICENCE.txt
easySum-0.2.5.dist-info/METADATA
easySum-0.2.5.dist-info/WHEEL
easySum-0.2.5.dist-info/top_level.txt
easySum-0.2.5.dist-info/RECORD
